oarepo_mapping_includes/__init__.py
oarepo_mapping_includes/api.py
oarepo_mapping_includes/ext.py
oarepo_mapping_includes/mapping_transformer.py
oarepo_mapping_includes/version.py
oarepo_mapping_includes-1.4.4.dist-info/LICENSE
oarepo_mapping_includes-1.4.4.dist-info/METADATA
oarepo_mapping_includes-1.4.4.dist-info/WHEEL
oarepo_mapping_includes-1.4.4.dist-info/entry_points.txt
oarepo_mapping_includes-1.4.4.dist-info/top_level.txt
oarepo_mapping_includes-1.4.4.dist-info/RECORD
