Metadata-Version: 2.1
Name: oarepo-mapping-includes
Version: 1.4.4
Summary: An inclusion mechanism for elasticsearch mappings
Home-page: https://github.com/oarepo/oarepo-mapping-includes
Author: Miroslav Simek
Author-email: miroslav.simek@vscht.cz
License: MIT
Platform: any
Classifier: Environment :: Web Environment
Classifier: Intended Audience :: Developers
Classifier: License :: OSI Approved :: MIT License
Classifier: Operating System :: OS Independent
Classifier: Programming Language :: Python
Classifier: Topic :: Internet :: WWW/HTTP :: Dynamic Content
Classifier: Topic :: Software Development :: Libraries :: Python Modules
Classifier: Programming Language :: Python :: 3
Classifier: Programming Language :: Python :: 3.8
Classifier: Development Status :: 4 - Beta
Requires-Dist: elasticsearch
Requires-Dist: deepmerge
Requires-Dist: NamedAtomicLock
Provides-Extra: tests
Requires-Dist: requests-mock ; extra == 'tests'
Requires-Dist: oarepo[tests] ; extra == 'tests'
